aiocamedomotic/__init__.py
aiocamedomotic/auth.py
aiocamedomotic/came_domotic_api.py
aiocamedomotic/errors.py
aiocamedomotic/models/__init__.py
aiocamedomotic/models/base.py
aiocamedomotic/models/light.py
aiocamedomotic/models/opening.py
aiocamedomotic/models/update.py
aiocamedomotic/utils.py
aiocamedomotic-1.1.1.dist-info/LICENSE
aiocamedomotic-1.1.1.dist-info/METADATA
aiocamedomotic-1.1.1.dist-info/WHEEL
aiocamedomotic-1.1.1.dist-info/RECORD
