Metadata-Version: 2.3
Name: aiocamedomotic
Version: 1.1.1
Summary: Python library to interact with a CAME ETI/Domo domotic server.
License: Apache-2.0
Keywords: CAME,ETI/Domo,domotic,home automation,home assistant,home-assistant
Author: camedomotic-unofficial
Author-email: camedomotic-unofficial@gmail.com
Maintainer: camedomotic-unofficial
Maintainer-email: camedomotic-unofficial@gmail.com
Requires-Python: >=3.12,<4.0
Classifier: Development Status :: 3 - Alpha
Classifier: Intended Audience :: Developers
Classifier: License :: OSI Approved :: Apache Software License
Classifier: Operating System :: OS Independent
Classifier: Programming Language :: Python :: 3
Classifier: Programming Language :: Python :: 3.12
Classifier: Programming Language :: Python :: 3.13
Classifier: Topic :: Home Automation
Classifier: Topic :: Software Development :: Libraries :: Python Modules
Requires-Dist: aiohttp (>=3.10.11,<4.0.0)
Requires-Dist: asyncio (>=3.4.3,<4.0.0)
Requires-Dist: cryptography (>=44.0.2,<45.0.0)
Requires-Dist: requests (>=2.32.2,<3.0.0)
Project-URL: Bug tracker, https://github.com/camedomotic-unofficial/aiocamedomotic/issues
Project-URL: Documentation, https://aiocamedomotic.readthedocs.io/latest/index.html
Project-URL: Homepage, https://github.com/camedomotic-unofficial/aiocamedomotic
Project-URL: Repository, https://github.com/camedomotic-unofficial/aiocamedomotic.git
